{
  "OBE83280581625102302": {
    "projectName": "官網訂房專案",
    "roomType": "M3｜M1",
    "phone": "0975897207",
    "updatedAt": "2026-04-17"
  },
  "OBE34960581625120301": {
    "projectName": "官網訂房專案",
    "roomType": "包棟",
    "phone": "0932583242",
    "updatedAt": "2026-04-17"
  },
  "OBE34200581625121002": {
    "projectName": "OTA串接專案",
    "roomType": "M3",
    "phone": "0902321035",
    "updatedAt": "2026-04-17"
  },
  "OBE32130581625121101": {
    "projectName": "OTA串接專案",
    "roomType": "O｜Z3",
    "phone": "0983368017",
    "updatedAt": "2026-04-17"
  },
  "OBE87010581625121701": {
    "projectName": "OTA串接專案",
    "roomType": "M3｜M1｜1",
    "phone": "",
    "updatedAt": "2026-04-17"
  },
  "OBE79010581625121801": {
    "projectName": "OTA串接專案",
    "roomType": "Z1｜Z3｜Z2｜Z5",
    "phone": "0906463977",
    "updatedAt": "2026-04-17"
  },
  "OBE46030581625121903": {
    "projectName": "官網訂房專案",
    "roomType": "M1｜M2",
    "phone": "0982279722",
    "updatedAt": "2026-04-17"
  },
  "OBE59370581625122603": {
    "projectName": "OTA串接專案",
    "roomType": "M1",
    "phone": "0908895286",
    "updatedAt": "2026-04-17"
  },
  "OBE08340581625122705": {
    "projectName": "OTA串接專案",
    "roomType": "M1",
    "phone": "0916901707",
    "updatedAt": "2026-04-17"
  },
  "OBE53660581625122706": {
    "projectName": "OTA串接專案",
    "roomType": "Z3｜Z1",
    "phone": "0975729822",
    "updatedAt": "2026-04-17"
  },
  "OBE65380581625122801": {
    "projectName": "OTA串接專案",
    "roomType": "Z3",
    "phone": "090597622007",
    "updatedAt": "2026-04-17"
  },
  "OBE92570581625122902": {
    "projectName": "OTA串接專案",
    "roomType": "M5",
    "phone": "0979829279",
    "updatedAt": "2026-04-17"
  },
  "OBE32080581625122903": {
    "projectName": "OTA串接專案",
    "roomType": "M3",
    "phone": "0929831124",
    "updatedAt": "2026-04-17"
  },
  "OBE95950581626010101": {
    "projectName": "OTA串接專案",
    "roomType": "M1",
    "phone": "0987515206",
    "updatedAt": "2026-04-17"
  },
  "OBE67120581626010102": {
    "projectName": "官網訂房專案",
    "roomType": "M1",
    "phone": "0902360665",
    "updatedAt": "2026-04-17"
  },
  "OBE40470581626010103": {
    "projectName": "OTA串接專案",
    "roomType": "M5",
    "phone": "0985952231",
    "updatedAt": "2026-04-17"
  },
  "OBE43400581626010105": {
    "projectName": "OTA串接專案",
    "roomType": "M5｜Z5",
    "phone": "0928192177",
    "updatedAt": "2026-04-17"
  },
  "OBE35010581626010202": {
    "projectName": "OTA串接專案",
    "roomType": "M3｜M1",
    "phone": "0933656991",
    "updatedAt": "2026-04-17"
  },
  "OBE14360581626010204": {
    "projectName": "OTA串接專案",
    "roomType": "M3",
    "phone": "0921549767",
    "updatedAt": "2026-04-17"
  },
  "OBE20100581626010701": {
    "projectName": "OTA串接專案",
    "roomType": "M1｜M3｜Z1｜Z3",
    "phone": "0919432806",
    "updatedAt": "2026-04-17"
  },
  "OBE89080581626010902": {
    "projectName": "OTA串接專案",
    "roomType": "Z3",
    "phone": "0978930028",
    "updatedAt": "2026-04-17"
  },
  "OBE99340581626010903": {
    "projectName": "OTA串接專案",
    "roomType": "M1｜M3｜Z1",
    "phone": "0989720912",
    "updatedAt": "2026-04-17"
  },
  "OBE57630581626011001": {
    "projectName": "官網訂房專案",
    "roomType": "M3｜Z1｜O",
    "phone": "0987867097",
    "updatedAt": "2026-04-17"
  },
  "OBE63220581626011002": {
    "projectName": "官網訂房專案 - 2人入住",
    "roomType": "Z2",
    "phone": "0987867097",
    "updatedAt": "2026-04-17"
  },
  "OBE05680581626011003": {
    "projectName": "官網訂房專案",
    "roomType": "1｜M2｜M5",
    "phone": "0987867097",
    "updatedAt": "2026-04-17"
  },
  "OBE15730581626011004": {
    "projectName": "官網訂房專案",
    "roomType": "M1",
    "phone": "0987867097",
    "updatedAt": "2026-04-17"
  },
  "OBE97970581626011005": {
    "projectName": "官網訂房專案",
    "roomType": "包棟",
    "phone": "0918788156",
    "updatedAt": "2026-04-17"
  },
  "OBE63040581626011101": {
    "projectName": "官網訂房專案",
    "roomType": "M1",
    "phone": "0905321939",
    "updatedAt": "2026-04-17"
  },
  "OBE56480581626011102": {
    "projectName": "官網訂房專案",
    "roomType": "M3｜M1",
    "phone": "0958256587",
    "updatedAt": "2026-04-17"
  },
  "OBE25880581626011203": {
    "projectName": "官網訂房專案",
    "roomType": "M3｜M1",
    "phone": "0927072213",
    "updatedAt": "2026-04-17"
  },
  "OBE91910581626011301": {
    "projectName": "官網訂房專案",
    "roomType": "M5",
    "phone": "0989708539",
    "updatedAt": "2026-04-17"
  },
  "OBE32540581626011302": {
    "projectName": "OTA串接專案",
    "roomType": "M2",
    "phone": "",
    "updatedAt": "2026-04-17"
  },
  "OBE94040581626011402": {
    "projectName": "OTA串接專案",
    "roomType": "M3｜M1｜M5",
    "phone": "0933661195",
    "updatedAt": "2026-04-17"
  },
  "OBE40390581626011501": {
    "projectName": "OTA串接專案",
    "roomType": "M1｜M3",
    "phone": "0917006300",
    "updatedAt": "2026-04-17"
  },
  "OBE57520581626011503": {
    "projectName": "官網訂房專案",
    "roomType": "M3｜M1",
    "phone": "0917006300",
    "updatedAt": "2026-04-17"
  },
  "OBE38370581626011701": {
    "projectName": "官網訂房專案 -  4人入住",
    "roomType": "M2",
    "phone": "0916668550",
    "updatedAt": "2026-04-17"
  },
  "OBE54170581626011802": {
    "projectName": "官網訂房專案",
    "roomType": "M3",
    "phone": "0973886612",
    "updatedAt": "2026-04-17"
  },
  "OBE53940581626011904": {
    "projectName": "OTA串接專案",
    "roomType": "Z2",
    "phone": "0963325921",
    "updatedAt": "2026-04-17"
  },
  "OBE90480581626012105": {
    "projectName": "OTA串接專案",
    "roomType": "Z1",
    "phone": "0979625736",
    "updatedAt": "2026-04-17"
  },
  "OBE30510581626012107": {
    "projectName": "官網訂房專案 - 2人入住",
    "roomType": "M2",
    "phone": "0933303651",
    "updatedAt": "2026-04-17"
  },
  "OBE26360581626012108": {
    "projectName": "OTA串接專案",
    "roomType": "Z3｜1",
    "phone": "0989272310",
    "updatedAt": "2026-04-17"
  },
  "OBE35850581626012201": {
    "projectName": "官網訂房專案",
    "roomType": "M3",
    "phone": "0975015929",
    "updatedAt": "2026-04-17"
  },
  "OBE53930581626012204": {
    "projectName": "官網訂房專案",
    "roomType": "M1",
    "phone": "0980760088",
    "updatedAt": "2026-04-17"
  },
  "OBE50680581626012401": {
    "projectName": "OTA串接專案",
    "roomType": "Z2",
    "phone": "0937150946",
    "updatedAt": "2026-04-17"
  },
  "OBE41990581626012503": {
    "projectName": "官網訂房專案",
    "roomType": "Z1｜M1｜M3",
    "phone": "0970323637",
    "updatedAt": "2026-04-17"
  },
  "OBE40660581626012601": {
    "projectName": "官網訂房專案｜官網訂房專案 -  4人入住",
    "roomType": "Z3｜M2",
    "phone": "0973234646",
    "updatedAt": "2026-04-17"
  },
  "OBE35760581626012602": {
    "projectName": "官網訂房專案",
    "roomType": "包棟",
    "phone": "0912855042",
    "updatedAt": "2026-04-17"
  },
  "OBE79900581626012603": {
    "projectName": "OTA串接專案",
    "roomType": "M1",
    "phone": "0975241370",
    "updatedAt": "2026-04-17"
  },
  "OBE31630581626012704": {
    "projectName": "官網訂房專案",
    "roomType": "M1",
    "phone": "0916665317",
    "updatedAt": "2026-04-17"
  },
  "OBE66890581626012901": {
    "projectName": "OTA串接專案",
    "roomType": "Z2",
    "phone": "0978674834",
    "updatedAt": "2026-04-17"
  },
  "OBE66490581626012902": {
    "projectName": "OTA串接專案",
    "roomType": "M5",
    "phone": "0916592423",
    "updatedAt": "2026-04-17"
  },
  "OBE72890581626013002": {
    "projectName": "OTA串接專案",
    "roomType": "Z1｜M1｜M3",
    "phone": "0970063817",
    "updatedAt": "2026-04-17"
  },
  "OBE49750581626013101": {
    "projectName": "官網訂房專案",
    "roomType": "M1｜M3",
    "phone": "09333735",
    "updatedAt": "2026-04-17"
  },
  "OBE91040581626013102": {
    "projectName": "OTA串接專案",
    "roomType": "M3",
    "phone": "0920693162",
    "updatedAt": "2026-04-17"
  },
  "OBE73600581626013103": {
    "projectName": "官網訂房專案",
    "roomType": "M1",
    "phone": "0939357828",
    "updatedAt": "2026-04-17"
  },
  "OBE79420581626020101": {
    "projectName": "OTA串接專案",
    "roomType": "M1",
    "phone": "0907948988",
    "updatedAt": "2026-04-17"
  },
  "OBE81940581626020103": {
    "projectName": "OTA串接專案",
    "roomType": "Z5",
    "phone": "0988772455",
    "updatedAt": "2026-04-17"
  },
  "OBE88490581626020204": {
    "projectName": "OTA串接專案",
    "roomType": "M1",
    "phone": "0988527731",
    "updatedAt": "2026-04-17"
  },
  "OBE78010581626020205": {
    "projectName": "OTA串接專案",
    "roomType": "M2",
    "phone": "0911787912",
    "updatedAt": "2026-04-17"
  },
  "OBE78940581626020401": {
    "projectName": "OTA串接專案",
    "roomType": "Z5",
    "phone": "0970887026",
    "updatedAt": "2026-04-17"
  },
  "OBE79200581626020404": {
    "projectName": "官網訂房專案",
    "roomType": "Z1",
    "phone": "0907810327",
    "updatedAt": "2026-04-17"
  },
  "OBE14470581626020407": {
    "projectName": "OTA串接專案",
    "roomType": "M2｜Z2｜M5｜Z5",
    "phone": "0926123819",
    "updatedAt": "2026-04-17"
  },
  "OBE82600581626020408": {
    "projectName": "官網訂房專案",
    "roomType": "Z1",
    "phone": "0976265858",
    "updatedAt": "2026-04-17"
  },
  "OBE14600581626020502": {
    "projectName": "官網訂房專案",
    "roomType": "Z1",
    "phone": "0901212530",
    "updatedAt": "2026-04-17"
  },
  "OBE82690581626020504": {
    "projectName": "官網訂房專案",
    "roomType": "M3",
    "phone": "0976466189",
    "updatedAt": "2026-04-17"
  },
  "OBE58300581626020505": {
    "projectName": "OTA串接專案",
    "roomType": "M2",
    "phone": "0909265576",
    "updatedAt": "2026-04-17"
  },
  "OBE59980581626020601": {
    "projectName": "OTA串接專案",
    "roomType": "Z2",
    "phone": "0984381805",
    "updatedAt": "2026-04-17"
  },
  "OBE73840581626020602": {
    "projectName": "OTA串接專案",
    "roomType": "1",
    "phone": "0970521949",
    "updatedAt": "2026-04-17"
  },
  "OBE88240581626020801": {
    "projectName": "OTA串接專案",
    "roomType": "Z3｜Z1｜Z5",
    "phone": "0958277816",
    "updatedAt": "2026-04-17"
  },
  "OBE64220581626020802": {
    "projectName": "OTA串接專案",
    "roomType": "Z3｜Z1",
    "phone": "0919675880",
    "updatedAt": "2026-04-17"
  },
  "OBE75090581626021003": {
    "projectName": "OTA串接專案",
    "roomType": "M2",
    "phone": "0901238828",
    "updatedAt": "2026-04-17"
  },
  "OBE44310581626021004": {
    "projectName": "OTA串接專案",
    "roomType": "M1",
    "phone": "0918825051",
    "updatedAt": "2026-04-17"
  },
  "OBE13790581626021005": {
    "projectName": "OTA串接專案",
    "roomType": "Z3｜Z1",
    "phone": "0905839083",
    "updatedAt": "2026-04-17"
  },
  "OBE79000581626021201": {
    "projectName": "OTA串接專案",
    "roomType": "M2｜Z2",
    "phone": "0963098340",
    "updatedAt": "2026-04-17"
  },
  "OBE48450581626021202": {
    "projectName": "官網訂房專案",
    "roomType": "M1",
    "phone": "0918383599",
    "updatedAt": "2026-04-17"
  },
  "OBE75770581626021204": {
    "projectName": "OTA串接專案",
    "roomType": "O",
    "phone": "",
    "updatedAt": "2026-04-17"
  },
  "OBE70670581626021205": {
    "projectName": "官網訂房專案",
    "roomType": "Z3",
    "phone": "0983589994",
    "updatedAt": "2026-04-17"
  },
  "OBE71410581626021402": {
    "projectName": "官網訂房專案",
    "roomType": "M1",
    "phone": "0958633115",
    "updatedAt": "2026-04-17"
  },
  "OBE83140581626021403": {
    "projectName": "OTA串接專案",
    "roomType": "1",
    "phone": "",
    "updatedAt": "2026-04-17"
  },
  "OBE35100581626021501": {
    "projectName": "OTA串接專案",
    "roomType": "1｜M3｜Z1",
    "phone": "0970022078",
    "updatedAt": "2026-04-17"
  },
  "OBE12350581626021502": {
    "projectName": "官網訂房專案",
    "roomType": "M3",
    "phone": "0958831070",
    "updatedAt": "2026-04-17"
  },
  "OBE35810581626021602": {
    "projectName": "OTA串接專案",
    "roomType": "M3",
    "phone": "0978382055",
    "updatedAt": "2026-04-17"
  },
  "OBE69300581626021702": {
    "projectName": "OTA串接專案",
    "roomType": "Z1",
    "phone": "0983102850",
    "updatedAt": "2026-04-17"
  },
  "OBE63100581626021703": {
    "projectName": "官網訂房專案",
    "roomType": "Z1",
    "phone": "0933373395",
    "updatedAt": "2026-04-17"
  },
  "OBE37990581626021801": {
    "projectName": "OTA串接專案",
    "roomType": "M3",
    "phone": "0968955363",
    "updatedAt": "2026-04-17"
  },
  "OBE44980581626021802": {
    "projectName": "OTA串接專案",
    "roomType": "M2",
    "phone": "0981466169",
    "updatedAt": "2026-04-17"
  },
  "OBE10820581626021901": {
    "projectName": "官網訂房專案｜官網訂房專案 -  4人入住",
    "roomType": "Z1｜Z2",
    "phone": "0977239289",
    "updatedAt": "2026-04-17"
  },
  "OBE09460581626022101": {
    "projectName": "OTA串接專案",
    "roomType": "Z1｜M2",
    "phone": "0988841712",
    "updatedAt": "2026-04-17"
  },
  "OBE22690581626022102": {
    "projectName": "OTA串接專案",
    "roomType": "Z3｜Z1",
    "phone": "",
    "updatedAt": "2026-04-17"
  },
  "OBE69450581626022201": {
    "projectName": "OTA串接專案",
    "roomType": "Z1",
    "phone": "0963046441",
    "updatedAt": "2026-04-17"
  },
  "OBE33320581626022202": {
    "projectName": "OTA串接專案",
    "roomType": "M2｜M5",
    "phone": "0983746228",
    "updatedAt": "2026-04-17"
  },
  "OBE86390581626022301": {
    "projectName": "OTA串接專案",
    "roomType": "1",
    "phone": "0987565917",
    "updatedAt": "2026-04-17"
  },
  "OBE99470581626022302": {
    "projectName": "OTA串接專案",
    "roomType": "Z3",
    "phone": "0987763955",
    "updatedAt": "2026-04-17"
  },
  "OBE49740581626022303": {
    "projectName": "官網訂房專案",
    "roomType": "M2",
    "phone": "0960995207",
    "updatedAt": "2026-04-17"
  },
  "OBE05060581626022304": {
    "projectName": "OTA串接專案",
    "roomType": "O",
    "phone": "0978364186",
    "updatedAt": "2026-04-17"
  },
  "OBE11420581626022402": {
    "projectName": "OTA串接專案",
    "roomType": "1",
    "phone": "0963334436",
    "updatedAt": "2026-04-17"
  },
  "OBE63910581626022403": {
    "projectName": "OTA串接專案",
    "roomType": "1｜M1",
    "phone": "0965587272",
    "updatedAt": "2026-04-17"
  },
  "OBE09100581626022404": {
    "projectName": "OTA串接專案",
    "roomType": "Z3",
    "phone": "0917337196",
    "updatedAt": "2026-04-17"
  },
  "OBE10040581626022406": {
    "projectName": "OTA串接專案",
    "roomType": "O｜Z5",
    "phone": "0980321094",
    "updatedAt": "2026-04-17"
  },
  "OBE53600581626022501": {
    "projectName": "OTA串接專案",
    "roomType": "M2",
    "phone": "0967062858",
    "updatedAt": "2026-04-17"
  },
  "OBE60010581626022601": {
    "projectName": "OTA串接專案",
    "roomType": "Z2",
    "phone": "0975650121",
    "updatedAt": "2026-04-17"
  },
  "OBE63920581626022603": {
    "projectName": "官網訂房專案",
    "roomType": "M3｜M1",
    "phone": "0909683382",
    "updatedAt": "2026-04-17"
  },
  "OBE20880581626022604": {
    "projectName": "官網訂房專案",
    "roomType": "M1",
    "phone": "0930226983",
    "updatedAt": "2026-04-17"
  },
  "OBE10110581626022605": {
    "projectName": "OTA串接專案",
    "roomType": "M5",
    "phone": "0911939217",
    "updatedAt": "2026-04-17"
  },
  "OBE54460581626022606": {
    "projectName": "OTA串接專案",
    "roomType": "M2",
    "phone": "0968926188",
    "updatedAt": "2026-04-17"
  },
  "OBE88490581626022701": {
    "projectName": "官網訂房專案",
    "roomType": "M3",
    "phone": "0976137702",
    "updatedAt": "2026-04-17"
  },
  "OBE19610581626022702": {
    "projectName": "官網訂房專案 - 2人入住",
    "roomType": "Z2",
    "phone": "0978674834",
    "updatedAt": "2026-04-17"
  },
  "OBE28080581626022705": {
    "projectName": "OTA串接專案",
    "roomType": "O",
    "phone": "0980384226",
    "updatedAt": "2026-04-17"
  },
  "OBE62220581626022801": {
    "projectName": "OTA串接專案",
    "roomType": "M5｜Z5",
    "phone": "0900305131",
    "updatedAt": "2026-04-17"
  },
  "OBE28350581626022804": {
    "projectName": "官網訂房專案",
    "roomType": "M1",
    "phone": "0903985392",
    "updatedAt": "2026-04-17"
  },
  "OBE63170581626030201": {
    "projectName": "官網訂房專案",
    "roomType": "Z3｜Z1",
    "phone": "0987989183",
    "updatedAt": "2026-04-17"
  },
  "OBE69680581626030202": {
    "projectName": "OTA串接專案",
    "roomType": "Z2｜M2｜M5｜Z5",
    "phone": "0958876909",
    "updatedAt": "2026-04-17"
  },
  "OBE92250581626030203": {
    "projectName": "OTA串接專案",
    "roomType": "O",
    "phone": "0903933186",
    "updatedAt": "2026-04-17"
  },
  "OBE74390581626030204": {
    "projectName": "OTA串接專案",
    "roomType": "Z2",
    "phone": "0909409411",
    "updatedAt": "2026-04-17"
  },
  "OBE52020581626030205": {
    "projectName": "OTA串接專案",
    "roomType": "M5",
    "phone": "0963010430",
    "updatedAt": "2026-04-17"
  },
  "OBE94650581626030207": {
    "projectName": "官網訂房專案",
    "roomType": "O｜Z3",
    "phone": "0966009689",
    "updatedAt": "2026-04-17"
  },
  "OBE78090581626030303": {
    "projectName": "OTA串接專案",
    "roomType": "Z3",
    "phone": "0905801992",
    "updatedAt": "2026-04-17"
  },
  "OBE84430581626030402": {
    "projectName": "官網訂房專案",
    "roomType": "M1",
    "phone": "0982534560",
    "updatedAt": "2026-04-17"
  },
  "OBE76940581626030403": {
    "projectName": "OTA串接專案",
    "roomType": "Z3",
    "phone": "0975413895",
    "updatedAt": "2026-04-17"
  },
  "OBE95220581626030405": {
    "projectName": "OTA串接專案",
    "roomType": "Z3",
    "phone": "0907707857",
    "updatedAt": "2026-04-17"
  },
  "OBE25480581626030504": {
    "projectName": "OTA串接專案",
    "roomType": "Z3",
    "phone": "0908528850",
    "updatedAt": "2026-04-17"
  },
  "OBE29600581626030505": {
    "projectName": "OTA串接專案",
    "roomType": "M5",
    "phone": "0978605833",
    "updatedAt": "2026-04-17"
  },
  "OBE39090581626030506": {
    "projectName": "官網訂房專案",
    "roomType": "M3",
    "phone": "0975596909",
    "updatedAt": "2026-04-17"
  },
  "OBE57670581626030603": {
    "projectName": "OTA串接專案",
    "roomType": "M1",
    "phone": "0934335313",
    "updatedAt": "2026-04-17"
  },
  "OBE09020581626030605": {
    "projectName": "OTA串接專案",
    "roomType": "1",
    "phone": "",
    "updatedAt": "2026-04-17"
  },
  "OBE85360581626030702": {
    "projectName": "OTA串接專案",
    "roomType": "M3｜Z1",
    "phone": "0984266711",
    "updatedAt": "2026-04-17"
  },
  "OBE67210581626030704": {
    "projectName": "OTA串接專案",
    "roomType": "Z2",
    "phone": "0963731858",
    "updatedAt": "2026-04-17"
  },
  "OBE56980581626030802": {
    "projectName": "官網訂房專案",
    "roomType": "M1",
    "phone": "0910801202",
    "updatedAt": "2026-04-17"
  },
  "OBE27710581626030804": {
    "projectName": "OTA串接專案",
    "roomType": "O",
    "phone": "0913088619",
    "updatedAt": "2026-04-17"
  },
  "OBE06140581626030805": {
    "projectName": "OTA串接專案",
    "roomType": "Z1",
    "phone": "0930762915",
    "updatedAt": "2026-04-17"
  },
  "OBE08360581626030901": {
    "projectName": "OTA串接專案",
    "roomType": "Z1",
    "phone": "0965322645",
    "updatedAt": "2026-04-17"
  },
  "OBE28080581626030902": {
    "projectName": "官網訂房專案",
    "roomType": "M3",
    "phone": "0979729155",
    "updatedAt": "2026-04-17"
  },
  "OBE43410581626030905": {
    "projectName": "OTA串接專案",
    "roomType": "1",
    "phone": "0972232226",
    "updatedAt": "2026-04-17"
  },
  "OBE14360581626030907": {
    "projectName": "OTA串接專案",
    "roomType": "M5",
    "phone": "0975337283",
    "updatedAt": "2026-04-17"
  },
  "OBE11270581626030908": {
    "projectName": "官網訂房專案",
    "roomType": "M3",
    "phone": "09333735",
    "updatedAt": "2026-04-17"
  },
  "OBE51200581626031102": {
    "projectName": "官網訂房專案 - 2人入住",
    "roomType": "M2",
    "phone": "0989788810",
    "updatedAt": "2026-04-17"
  },
  "OBE70000581626031103": {
    "projectName": "官網訂房專案 -  4人入住",
    "roomType": "Z2｜M5",
    "phone": "0983791165",
    "updatedAt": "2026-04-17"
  },
  "OBE84620581626031104": {
    "projectName": "OTA串接專案",
    "roomType": "1｜M5",
    "phone": "0937768656",
    "updatedAt": "2026-04-17"
  },
  "OBE46780581626031201": {
    "projectName": "OTA串接專案",
    "roomType": "M1",
    "phone": "0918299969",
    "updatedAt": "2026-04-17"
  },
  "OBE65850581626031203": {
    "projectName": "OTA串接專案",
    "roomType": "M1",
    "phone": "0903383406",
    "updatedAt": "2026-04-17"
  },
  "OBE05120581626031204": {
    "projectName": "OTA串接專案",
    "roomType": "M5",
    "phone": "0933494756",
    "updatedAt": "2026-04-17"
  },
  "OBE97030581626031301": {
    "projectName": "OTA串接專案",
    "roomType": "Z3",
    "phone": "0972502117",
    "updatedAt": "2026-04-17"
  },
  "OBE54360581626031302": {
    "projectName": "OTA串接專案",
    "roomType": "1",
    "phone": "0919248755",
    "updatedAt": "2026-04-17"
  },
  "OBE12960581626031402": {
    "projectName": "OTA串接專案",
    "roomType": "M1",
    "phone": "0955062530",
    "updatedAt": "2026-04-17"
  },
  "OBE14470581626031604": {
    "projectName": "官網訂房專案 -  4人入住",
    "roomType": "Z5",
    "phone": "0930096102",
    "updatedAt": "2026-04-17"
  },
  "OBE60850581626031606": {
    "projectName": "OTA串接專案",
    "roomType": "1",
    "phone": "0984385722",
    "updatedAt": "2026-04-17"
  },
  "OBE92120581626031701": {
    "projectName": "OTA串接專案",
    "roomType": "M2",
    "phone": "0975826104",
    "updatedAt": "2026-04-17"
  },
  "OBE93960581626031702": {
    "projectName": "OTA串接專案",
    "roomType": "Z1",
    "phone": "0918465650",
    "updatedAt": "2026-04-17"
  },
  "OBE68830581626031704": {
    "projectName": "OTA串接專案",
    "roomType": "M1",
    "phone": "0988780574",
    "updatedAt": "2026-04-17"
  },
  "OBE90130581626031708": {
    "projectName": "OTA串接專案",
    "roomType": "O",
    "phone": "0978083152",
    "updatedAt": "2026-04-17"
  },
  "OBE21230581626031705": {
    "projectName": "OTA串接專案",
    "roomType": "1｜Z1｜Z3｜O",
    "phone": "0986329392",
    "updatedAt": "2026-04-17"
  },
  "OBE12030581626031710": {
    "projectName": "OTA串接專案",
    "roomType": "Z3",
    "phone": "0966610005",
    "updatedAt": "2026-04-17"
  },
  "OBE86230581626031707": {
    "projectName": "OTA串接專案",
    "roomType": "M1｜M3",
    "phone": "0956583880",
    "updatedAt": "2026-04-17"
  },
  "OBE55380581626031711": {
    "projectName": "OTA串接專案",
    "roomType": "M3",
    "phone": "0917376680",
    "updatedAt": "2026-04-17"
  },
  "OBE57710581626031709": {
    "projectName": "官網訂房專案｜官網訂房專案 - 2人入住",
    "roomType": "O｜M2｜Z2｜Z5",
    "phone": "0931158017",
    "updatedAt": "2026-04-17"
  },
  "OBE77290581626031802": {
    "projectName": "官網訂房專案",
    "roomType": "包棟",
    "phone": "0909712880",
    "updatedAt": "2026-04-17"
  },
  "OBE41140581626031803": {
    "projectName": "OTA串接專案",
    "roomType": "M2｜M5｜Z5",
    "phone": "0928598510",
    "updatedAt": "2026-04-17"
  },
  "OBE78720581626031901": {
    "projectName": "OTA串接專案",
    "roomType": "M1",
    "phone": "0983662019",
    "updatedAt": "2026-04-17"
  },
  "OBE53130581626031902": {
    "projectName": "OTA串接專案",
    "roomType": "Z3｜O",
    "phone": "0928801996",
    "updatedAt": "2026-04-17"
  },
  "OBE41480581626031903": {
    "projectName": "OTA串接專案",
    "roomType": "O｜M3｜Z1｜Z2",
    "phone": "0976039788",
    "updatedAt": "2026-04-17"
  },
  "OBE14990581626032102": {
    "projectName": "官網訂房專案 - 2人入住",
    "roomType": "Z2",
    "phone": "0955991620",
    "updatedAt": "2026-04-17"
  },
  "OBE57450581626032103": {
    "projectName": "OTA串接專案",
    "roomType": "1",
    "phone": "0939401700",
    "updatedAt": "2026-04-17"
  },
  "OBE83240581626032201": {
    "projectName": "OTA串接專案",
    "roomType": "M1｜M2",
    "phone": "0976226406",
    "updatedAt": "2026-04-17"
  },
  "OBE22970581626032202": {
    "projectName": "OTA串接專案",
    "roomType": "Z1",
    "phone": "0988023993",
    "updatedAt": "2026-04-17"
  },
  "OBE07670581626032204": {
    "projectName": "OTA串接專案",
    "roomType": "Z5",
    "phone": "0953885385",
    "updatedAt": "2026-04-17"
  },
  "OBE03310581626032205": {
    "projectName": "OTA串接專案",
    "roomType": "M2｜Z2",
    "phone": "0905880987",
    "updatedAt": "2026-04-17"
  },
  "OBE33430581626032301": {
    "projectName": "OTA串接專案",
    "roomType": "Z5",
    "phone": "0958100462",
    "updatedAt": "2026-04-17"
  },
  "OBE35540581626032302": {
    "projectName": "OTA串接專案",
    "roomType": "O",
    "phone": "0920668795",
    "updatedAt": "2026-04-17"
  },
  "OBE96800581626032304": {
    "projectName": "OTA串接專案",
    "roomType": "Z3",
    "phone": "0933656991",
    "updatedAt": "2026-04-17"
  },
  "OBE63350581626032305": {
    "projectName": "官網訂房專案",
    "roomType": "包棟",
    "phone": "09333735",
    "updatedAt": "2026-04-17"
  },
  "OBE99320581626032303": {
    "projectName": "OTA串接專案",
    "roomType": "1｜M1｜M3｜Z1｜Z3",
    "phone": "0955458026",
    "updatedAt": "2026-04-17"
  },
  "OBE12890581626032306": {
    "projectName": "官網訂房專案",
    "roomType": "1",
    "phone": "0983656990",
    "updatedAt": "2026-04-17"
  },
  "OBE81590581626032401": {
    "projectName": "官網訂房專案 - 2人入住｜官網訂房專案 -  4人入住",
    "roomType": "Z5｜M5",
    "phone": "0906883655",
    "updatedAt": "2026-04-17"
  },
  "OBE45420581626032406": {
    "projectName": "OTA串接專案",
    "roomType": "M3",
    "phone": "0930942479",
    "updatedAt": "2026-04-17"
  },
  "OBE18140581626032407": {
    "projectName": "OTA串接專案",
    "roomType": "Z3",
    "phone": "0988252220",
    "updatedAt": "2026-04-17"
  },
  "OBE77300581626032602": {
    "projectName": "OTA串接專案",
    "roomType": "1",
    "phone": "0911205422",
    "updatedAt": "2026-04-17"
  },
  "OBE42310581626032603": {
    "projectName": "OTA串接專案",
    "roomType": "1",
    "phone": "0931969050",
    "updatedAt": "2026-04-17"
  },
  "OBE14790581626032604": {
    "projectName": "OTA串接專案",
    "roomType": "1",
    "phone": "",
    "updatedAt": "2026-04-17"
  },
  "OBE18660581626032701": {
    "projectName": "OTA串接專案",
    "roomType": "1｜M2",
    "phone": "0905256150",
    "updatedAt": "2026-04-17"
  },
  "OBE55370581626032903": {
    "projectName": "OTA串接專案",
    "roomType": "Z1",
    "phone": "0966582057",
    "updatedAt": "2026-04-17"
  },
  "OBE21890581626032904": {
    "projectName": "OTA串接專案",
    "roomType": "1｜O｜M1｜M5",
    "phone": "0939606098",
    "updatedAt": "2026-04-17"
  },
  "OBE77970581626033002": {
    "projectName": "OTA串接專案",
    "roomType": "1",
    "phone": "",
    "updatedAt": "2026-04-17"
  },
  "OBE64300581626033003": {
    "projectName": "OTA串接專案",
    "roomType": "M5",
    "phone": "+8522035640799",
    "updatedAt": "2026-04-17"
  },
  "OBE64570581626033102": {
    "projectName": "OTA串接專案",
    "roomType": "Z2｜M5",
    "phone": "0930082945",
    "updatedAt": "2026-04-17"
  },
  "OBE43150581626040101": {
    "projectName": "OTA串接專案",
    "roomType": "Z1",
    "phone": "0918101118",
    "updatedAt": "2026-04-17"
  },
  "OBE54650581626040102": {
    "projectName": "官網訂房專案",
    "roomType": "Z3",
    "phone": "0921057953",
    "updatedAt": "2026-04-17"
  },
  "OBE03480581626040103": {
    "projectName": "OTA串接專案",
    "roomType": "Z1",
    "phone": "0911991138",
    "updatedAt": "2026-04-17"
  },
  "OBE44260581626040107": {
    "projectName": "OTA串接專案",
    "roomType": "M3",
    "phone": "0918269002",
    "updatedAt": "2026-04-17"
  },
  "OBE10140581626040201": {
    "projectName": "OTA串接專案",
    "roomType": "Z3",
    "phone": "0936226018",
    "updatedAt": "2026-04-17"
  },
  "OBE10180581626040202": {
    "projectName": "OTA串接專案",
    "roomType": "Z2",
    "phone": "0989901328",
    "updatedAt": "2026-04-17"
  },
  "OBE86450581626040203": {
    "projectName": "OTA串接專案",
    "roomType": "M3",
    "phone": "0973730236",
    "updatedAt": "2026-04-17"
  },
  "OBE44140581626040301": {
    "projectName": "官網訂房專案",
    "roomType": "Z1",
    "phone": "0987867097",
    "updatedAt": "2026-04-17"
  },
  "OBE99700581626040502": {
    "projectName": "官網訂房專案",
    "roomType": "O",
    "phone": "0981227978",
    "updatedAt": "2026-04-17"
  },
  "OBE93790581626040503": {
    "projectName": "OTA串接專案",
    "roomType": "M1",
    "phone": "0900766726",
    "updatedAt": "2026-04-17"
  },
  "OBE98320581626040504": {
    "projectName": "OTA串接專案",
    "roomType": "M5｜Z5",
    "phone": "0965599885",
    "updatedAt": "2026-04-17"
  },
  "OBE23480581626040601": {
    "projectName": "OTA串接專案",
    "roomType": "M1",
    "phone": "0920168183",
    "updatedAt": "2026-04-17"
  },
  "OBE83410581626040602": {
    "projectName": "OTA串接專案",
    "roomType": "O",
    "phone": "0928873333",
    "updatedAt": "2026-04-17"
  },
  "OBE17140581626040603": {
    "projectName": "OTA串接專案",
    "roomType": "M3",
    "phone": "0927390829",
    "updatedAt": "2026-04-17"
  },
  "OBE66530581626040604": {
    "projectName": "OTA串接專案",
    "roomType": "1｜M1",
    "phone": "0963924450",
    "updatedAt": "2026-04-17"
  },
  "OBE11970581626040606": {
    "projectName": "OTA串接專案",
    "roomType": "M1",
    "phone": "",
    "updatedAt": "2026-04-17"
  },
  "OBE85940581626040607": {
    "projectName": "OTA串接專案",
    "roomType": "Z3｜O",
    "phone": "",
    "updatedAt": "2026-04-17"
  },
  "OBE77400581626040701": {
    "projectName": "OTA串接專案",
    "roomType": "Z2",
    "phone": "0911991138",
    "updatedAt": "2026-04-17"
  },
  "OBE51810581626040801": {
    "projectName": "OTA串接專案",
    "roomType": "M2",
    "phone": "0919431743",
    "updatedAt": "2026-04-17"
  },
  "OBE44700581626040802": {
    "projectName": "官網訂房專案",
    "roomType": "M1｜M3",
    "phone": "0908359501",
    "updatedAt": "2026-04-17"
  },
  "OBE00350581626040805": {
    "projectName": "OTA串接專案",
    "roomType": "1",
    "phone": "0907092901",
    "updatedAt": "2026-04-17"
  },
  "OBE05130581626040804": {
    "projectName": "OTA串接專案",
    "roomType": "Z1｜M3",
    "phone": "0965137010",
    "updatedAt": "2026-04-17"
  },
  "OBE91120581626040807": {
    "projectName": "OTA串接專案",
    "roomType": "M3",
    "phone": "0911097880",
    "updatedAt": "2026-04-17"
  },
  "OBE28000581626040810": {
    "projectName": "OTA串接專案",
    "roomType": "O",
    "phone": "0931379960",
    "updatedAt": "2026-04-17"
  },
  "OBE04790581626040808": {
    "projectName": "OTA串接專案",
    "roomType": "Z3",
    "phone": "+652035640799",
    "updatedAt": "2026-04-17"
  },
  "OBE19470581626040811": {
    "projectName": "OTA串接專案",
    "roomType": "1",
    "phone": "",
    "updatedAt": "2026-04-17"
  },
  "OBE21750581626040902": {
    "projectName": "官網訂房專案 - 2人入住",
    "roomType": "M2",
    "phone": "0903137529",
    "updatedAt": "2026-04-17"
  },
  "OBE72860581626040903": {
    "projectName": "OTA串接專案",
    "roomType": "Z1",
    "phone": "0952176527",
    "updatedAt": "2026-04-17"
  },
  "OBE61260581626040904": {
    "projectName": "OTA串接專案",
    "roomType": "M3",
    "phone": "0975058759",
    "updatedAt": "2026-04-17"
  },
  "OBE18830581626041002": {
    "projectName": "官網訂房專案｜官網訂房專案 - 2人入住",
    "roomType": "O｜Z5",
    "phone": "0933373395",
    "updatedAt": "2026-04-17"
  },
  "OBE46540581626041003": {
    "projectName": "官網訂房專案｜官網訂房專案 - 2人入住｜官網訂房專案 -  4人入住",
    "roomType": "O｜Z2｜M5",
    "phone": "09333735",
    "updatedAt": "2026-04-17"
  },
  "OBE24320581626041006": {
    "projectName": "OTA串接專案",
    "roomType": "M1",
    "phone": "0970010626",
    "updatedAt": "2026-04-17"
  },
  "OBE92240581626041005": {
    "projectName": "官網訂房專案 - 2人入住",
    "roomType": "M5",
    "phone": "09333735",
    "updatedAt": "2026-04-17"
  },
  "OBE95980581626041007": {
    "projectName": "官網訂房專案",
    "roomType": "Z1｜Z3",
    "phone": "0978473539",
    "updatedAt": "2026-04-17"
  },
  "OBE15690581626041008": {
    "projectName": "OTA串接專案",
    "roomType": "Z5",
    "phone": "0915629678",
    "updatedAt": "2026-04-17"
  },
  "OBE87840581626041009": {
    "projectName": "OTA串接專案",
    "roomType": "M3",
    "phone": "0918085736",
    "updatedAt": "2026-04-17"
  },
  "OBE19230581626041102": {
    "projectName": "OTA串接專案",
    "roomType": "Z3｜Z2",
    "phone": "01176267",
    "updatedAt": "2026-04-17"
  },
  "OBE21900581626041105": {
    "projectName": "OTA串接專案",
    "roomType": "O",
    "phone": "",
    "updatedAt": "2026-04-17"
  },
  "OBE18720581626041106": {
    "projectName": "OTA串接專案",
    "roomType": "1",
    "phone": "0911175788",
    "updatedAt": "2026-04-17"
  },
  "OBE01480581626041201": {
    "projectName": "OTA串接專案",
    "roomType": "M2",
    "phone": "0958863831",
    "updatedAt": "2026-04-17"
  },
  "OBE35100581626041202": {
    "projectName": "OTA串接專案",
    "roomType": "M2",
    "phone": "0973905156",
    "updatedAt": "2026-04-17"
  },
  "OBE96240581626041203": {
    "projectName": "OTA串接專案",
    "roomType": "M3",
    "phone": "0988639552",
    "updatedAt": "2026-04-17"
  },
  "OBE82450581626041204": {
    "projectName": "OTA串接專案",
    "roomType": "Z1｜Z3",
    "phone": "",
    "updatedAt": "2026-04-17"
  },
  "OBE06480581626041301": {
    "projectName": "OTA串接專案",
    "roomType": "Z1",
    "phone": "0982375207",
    "updatedAt": "2026-04-17"
  },
  "OBE24040581626041303": {
    "projectName": "OTA串接專案",
    "roomType": "1",
    "phone": "0906515015",
    "updatedAt": "2026-04-17"
  },
  "OBE76990581626041502": {
    "projectName": "OTA串接專案",
    "roomType": "Z3｜Z1",
    "phone": "0928733059",
    "updatedAt": "2026-04-17"
  },
  "OBE87370581626041503": {
    "projectName": "OTA串接專案",
    "roomType": "M3｜M1",
    "phone": "0935909082",
    "updatedAt": "2026-04-17"
  },
  "OBE47760581626041505": {
    "projectName": "OTA串接專案",
    "roomType": "1",
    "phone": "0979955930",
    "updatedAt": "2026-04-17"
  },
  "OBE66690581626041504": {
    "projectName": "OTA串接專案",
    "roomType": "O",
    "phone": "0984257843",
    "updatedAt": "2026-04-17"
  },
  "OBE86370581626041506": {
    "projectName": "OTA串接專案",
    "roomType": "1",
    "phone": "",
    "updatedAt": "2026-04-17"
  },
  "OBE74380581626041507": {
    "projectName": "OTA串接專案",
    "roomType": "1｜Z1",
    "phone": "",
    "updatedAt": "2026-04-17"
  },
  "OBE90520581626041601": {
    "projectName": "OTA串接專案",
    "roomType": "1",
    "phone": "0955569229",
    "updatedAt": "2026-04-17"
  }
}